aiodogstatsd/__init__.py
aiodogstatsd/client.py
aiodogstatsd/compat.py
aiodogstatsd/contrib/__init__.py
aiodogstatsd/contrib/aiohttp.py
aiodogstatsd/contrib/starlette.py
aiodogstatsd/protocol.py
aiodogstatsd/py.typed
aiodogstatsd/typedefs.py
aiodogstatsd-0.16.0.dist-info/LICENSE
aiodogstatsd-0.16.0.dist-info/WHEEL
aiodogstatsd-0.16.0.dist-info/METADATA
aiodogstatsd-0.16.0.dist-info/RECORD
