Metadata-Version: 2.1
Name: aiodogstatsd
Version: 0.16.0
Summary: An asyncio-based client for sending metrics to StatsD with support of DogStatsD extension
Home-page: https://github.com/Gr1N/aiodogstatsd
License: MIT
Keywords: asyncio,statsd,statsd-client,statsd-metrics,dogstatsd
Author: Nikita Grishko
Author-email: gr1n@protonmail.com
Requires-Python: >=3.7,<4.0
Classifier: License :: OSI Approved :: MIT License
Classifier: Programming Language :: Python :: 3
Classifier: Programming Language :: Python :: 3.10
Classifier: Programming Language :: Python :: 3.7
Classifier: Programming Language :: Python :: 3.8
Classifier: Programming Language :: Python :: 3.9
Classifier: Topic :: Software Development :: Libraries :: Python Modules
Provides-Extra: aiohttp
Provides-Extra: starlette
Requires-Dist: aiohttp (>=3.0); extra == "aiohttp"
Requires-Dist: starlette (>=0.13); extra == "starlette"
Project-URL: Documentation, https://gr1n.github.io/aiodogstatsd
Project-URL: Repository, https://github.com/Gr1N/aiodogstatsd
